aio_avion/__init__.py
aio_avion/__main__.py
aio_avion/config.py
aio_avion/device.py
aio_avion/location.py
aio_avion/product.py
aio_avion/user_info.py
aio_avion-0.0.2.dist-info/METADATA
aio_avion-0.0.2.dist-info/WHEEL
aio_avion-0.0.2.dist-info/top_level.txt
aio_avion-0.0.2.dist-info/RECORD
