Metadata-Version: 2.1
Name: aio-avion
Version: 0.0.2
Summary: Python module to control Avi-on lights through the Wi-Fi bridge.
Home-page: https://github.com/deisterhold/aio_avion
Author: Daniel Eisterhold
Author-email: deisterhold@gmail.com
License: UNKNOWN
Project-URL: Bug Tracker, https://github.com/deisterhold/aio_avion/issues
Platform: UNKNOWN
Classifier: Programming Language :: Python :: 3
Classifier: License :: OSI Approved :: MIT License
Classifier: Operating System :: OS Independent
Requires-Python: >=3.6
